[{"id":"nbk-vl","name":"Truong trung hoc Chuyen Nguyen Binh Khiem","address":"Vinh Long","teachers":[{"id":"337829999","name":"Tran Van Thanh","schoolId":"nbk-vl"}],"numberOfStudent":2000},{"id":"nbk-qn","name":"Truong trung hoc Chuyen Nguyen Binh Khiem","address":"Quang Ngai","teachers":[{"id":"334442222","name":"Nguyen Thi Tho","schoolId":"nbk-qn"}],"numberOfStudent":2500},{"id":"bk-hcm","name":"Bach Khoa HCM","address":"HCM","teachers":[{"id":"285656690","name":"Huy","schoolId":"bk-hcm"}],"numberOfStudent":3000}]